lambeq/__init__.py
lambeq/cli.py
lambeq/typing.py
lambeq/version.py
lambeq/version.pyi
lambeq/ansatz/__init__.py
lambeq/ansatz/base.py
lambeq/ansatz/circuit.py
lambeq/ansatz/tensor.py
lambeq/backend/__init__.py
lambeq/backend/grammar.py
lambeq/backend/numerical_backend.py
lambeq/backend/pennylane.py
lambeq/backend/quantum.py
lambeq/backend/snake_removal.py
lambeq/backend/symbol.py
lambeq/backend/tensor.py
lambeq/backend/converters/__init__.py
lambeq/backend/converters/discopy.py
lambeq/backend/converters/tk.py
lambeq/backend/drawing/__init__.py
lambeq/backend/drawing/drawable.py
lambeq/backend/drawing/drawing.py
lambeq/backend/drawing/drawing_backend.py
lambeq/backend/drawing/helpers.py
lambeq/backend/drawing/mat_backend.py
lambeq/backend/drawing/text_printer.py
lambeq/backend/drawing/tikz_backend.py
lambeq/bobcat/__init__.py
lambeq/bobcat/fast_int_enum.py
lambeq/bobcat/grammar.py
lambeq/bobcat/lexicon.py
lambeq/bobcat/parser.py
lambeq/bobcat/rules.py
lambeq/bobcat/tagger.py
lambeq/bobcat/tree.py
lambeq/core/__init__.py
lambeq/core/globals.py
lambeq/core/types.py
lambeq/core/utils.py
lambeq/experimental/discocirc/__init__.py
lambeq/experimental/discocirc/coref_resolver.py
lambeq/experimental/discocirc/pregroup_tree_rewriter.py
lambeq/experimental/discocirc/reader.py
lambeq/oncilla/__init__.py
lambeq/oncilla/parser.py
lambeq/rewrite/__init__.py
lambeq/rewrite/base.py
lambeq/rewrite/rewrite_diagram.py
lambeq/text2diagram/__init__.py
lambeq/text2diagram/base.py
lambeq/text2diagram/ccg_parser.py
lambeq/text2diagram/ccg_rule.py
lambeq/text2diagram/ccg_tree.py
lambeq/text2diagram/ccg_type.py
lambeq/text2diagram/ccgbank_parser.py
lambeq/text2diagram/depccg_parser.py
lambeq/text2diagram/linear_reader.py
lambeq/text2diagram/pregroup_tree.py
lambeq/text2diagram/pregroup_tree_converter.py
lambeq/text2diagram/spiders_reader.py
lambeq/text2diagram/tree_reader.py
lambeq/text2diagram/web_parser.py
lambeq/text2diagram/model_based_reader/__init__.py
lambeq-0.5.0.dist-info/METADATA
lambeq-0.5.0.dist-info/WHEEL
lambeq-0.5.0.dist-info/entry_points.txt
lambeq-0.5.0.dist-info/top_level.txt
lambeq-0.5.0.dist-info/RECORD
