Metadata-Version: 2.4
Name: lambeq
Version: 0.5.0
Summary: A QNLP toolkit
Home-page: https://docs.quantinuum.com/lambeq/
Download-URL: https://pypi.org/project/lambeq
Author: Quantinuum QNLP team
Author-email: lambeq-support@quantinuum.com
License: Apache-2.0
Project-URL: Source Code, https://github.com/CQCL/lambeq
Keywords: category theory,ccg,circuits,combinatory categorial grammar,diagrams,discocat,language,linguistics,natural language processing,nlp,qnlp,quantum,quantum computing,quantum natural language processing,quantum nlp
Classifier: Development Status :: 5 - Production/Stable
Classifier: Environment :: Console
Classifier: Intended Audience :: Developers
Classifier: Intended Audience :: Science/Research
Classifier: License :: OSI Approved :: Apache Software License
Classifier: Operating System :: OS Independent
Classifier: Programming Language :: Python :: 3
Classifier: Programming Language :: Python :: 3.10
Classifier: Programming Language :: Python :: 3.11
Classifier: Programming Language :: Python :: 3.12
Classifier: Topic :: Scientific/Engineering
Requires-Python: >=3.10
Requires-Dist: matplotlib>=3.8
Requires-Dist: networkx
Requires-Dist: opt-einsum
Requires-Dist: packaging
Requires-Dist: pillow>=6.2.1
Requires-Dist: pyyaml
Requires-Dist: spacy>=3.0
Requires-Dist: tensornetwork
Requires-Dist: torch>=1.12.1
Requires-Dist: transformers!=4.51.0
Provides-Extra: extras
Requires-Dist: discopy>=1.1.7; extra == "extras"
Requires-Dist: jax<0.6.0; extra == "extras"
Requires-Dist: jaxlib<0.6.0; extra == "extras"
Requires-Dist: pennylane<0.37.0,>=0.29.1; extra == "extras"
Requires-Dist: pennylane-honeywell; extra == "extras"
Requires-Dist: pennylane-qiskit<0.37.0,>=0.29.1; extra == "extras"
Requires-Dist: pennylane-lightning<0.37.0,>=0.29.1; extra == "extras"
Requires-Dist: pytket>=1.31.0; extra == "extras"
Requires-Dist: pytket-qiskit>=0.21.0; extra == "extras"
Requires-Dist: qiskit-aer<0.17.0; extra == "extras"
Requires-Dist: qiskit-ibm-runtime<0.37.0; extra == "extras"
Requires-Dist: tensorboard>=2.7.0; extra == "extras"
Requires-Dist: tqdm; extra == "extras"
Provides-Extra: test
Requires-Dist: coverage[toml]; extra == "test"
Requires-Dist: pytest; extra == "test"
Provides-Extra: experimental
Requires-Dist: maverick-coref>=1.0.3; extra == "experimental"
Dynamic: download-url
